{ "compressionlevel":-1,
 "height":20,
 "infinite":true,
 "layers":[
        {
         "chunks":[
                {
                 "data":[0, 0, 0, 0, 0, 0, 0, 0, 0, 0, 0, 0, 0, 0, 0, 0,
                    0, 0, 0, 0, 0, 0, 0, 0, 0, 0, 0, 0, 0, 0, 0, 0,
                    0, 0, 0, 0, 0, 0, 0, 0, 0, 0, 0, 0, 0, 0, 0, 0,
                    0, 0, 0, 0, 0, 0, 0, 0, 0, 0, 0, 0, 0, 0, 0, 0,
                    0, 0, 0, 0, 0, 0, 0, 0, 0, 0, 5, 6, 6, 6, 6, 6,
                    0, 0, 0, 0, 0, 0, 0, 0, 0, 0, 30, 31, 31, 31, 31, 31,
                    0, 0, 0, 0, 0, 0, 0, 0, 0, 0, 30, 31, 31, 31, 31, 31,
                    0, 0, 0, 0, 0, 0, 0, 0, 0, 0, 30, 31, 31, 31, 31, 31,
                    0, 0, 0, 0, 0, 0, 0, 0, 0, 0, 30, 31, 31, 31, 31, 31,
                    0, 0, 0, 0, 0, 0, 0, 0, 0, 0, 30, 31, 31, 31, 31, 31,
                    0, 0, 0, 0, 0, 0, 0, 0, 0, 0, 30, 31, 31, 31, 31, 31,
                    0, 0, 0, 0, 0, 0, 0, 0, 0, 0, 30, 31, 31, 31, 31, 31,
                    0, 0, 0, 0, 0, 0, 0, 0, 0, 0, 0, 0, 0, 0, 0, 0,
                    0, 0, 0, 0, 0, 0, 0, 0, 0, 0, 0, 0, 0, 0, 0, 0,
                    0, 0, 0, 0, 0, 0, 0, 0, 0, 0, 0, 0, 0, 0, 0, 0,
                    0, 0, 0, 0, 0, 0, 0, 0, 0, 0, 0, 0, 0, 0, 0, 0],
                 "height":16,
                 "width":16,
                 "x":-32,
                 "y":0
                }, 
                {
                 "data":[0, 0, 0, 0, 0, 0, 0, 0, 0, 0, 0, 0, 0, 0, 253, 253,
                    0, 0, 0, 0, 0, 0, 0, 0, 0, 0, 0, 0, 0, 0, 0, 0,
                    0, 0, 0, 0, 0, 0, 0, 0, 0, 0, 0, 0, 0, 0, 0, 0,
                    0, 0, 0, 0, 0, 0, 0, 0, 0, 0, 0, 0, 0, 0, 0, 0,
                    6, 6, 6, 6, 6, 6, 6, 6, 6, 6, 6, 6, 7, 34, 5, 6,
                    31, 31, 31, 31, 31, 31, 31, 31, 31, 31, 31, 31, 31, 31, 31, 31,
                    31, 31, 31, 31, 31, 31, 31, 31, 31, 31, 31, 31, 31, 31, 31, 31,
                    31, 31, 31, 31, 31, 31, 31, 31, 31, 31, 31, 31, 31, 31, 31, 31,
                    31, 31, 31, 31, 31, 31, 31, 31, 31, 31, 31, 31, 31, 31, 31, 31,
                    31, 31, 31, 31, 31, 31, 31, 31, 31, 31, 31, 31, 31, 31, 31, 31,
                    31, 31, 31, 31, 31, 31, 31, 31, 31, 31, 31, 31, 31, 31, 31, 31,
                    31, 31, 31, 31, 31, 31, 31, 31, 31, 31, 31, 31, 31, 31, 31, 31,
                    0, 0, 0, 0, 0, 0, 0, 0, 0, 0, 0, 0, 0, 0, 0, 0,
                    0, 0, 0, 0, 0, 0, 0, 0, 0, 0, 0, 0, 0, 0, 0, 0,
                    0, 0, 0, 0, 0, 0, 0, 0, 0, 0, 0, 0, 0, 0, 0, 0,
                    0, 0, 0, 0, 0, 0, 0, 0, 0, 0, 0, 0, 0, 0, 0, 0],
                 "height":16,
                 "width":16,
                 "x":-16,
                 "y":0
                }, 
                {
                 "data":[253, 253, 253, 253, 253, 253, 0, 0, 0, 0, 0, 0, 0, 0, 0, 0,
                    0, 0, 0, 0, 0, 0, 0, 0, 0, 0, 0, 0, 0, 0, 0, 0,
                    0, 0, 0, 0, 0, 0, 0, 0, 0, 0, 0, 0, 0, 0, 0, 0,
                    0, 0, 0, 0, 0, 0, 0, 0, 0, 0, 0, 0, 0, 0, 0, 0,
                    6, 6, 6, 6, 6, 6, 7, 34, 5, 6, 6, 6, 6, 6, 6, 6,
                    31, 31, 31, 31, 31, 31, 81, 59, 60, 31, 31, 31, 31, 31, 31, 31,
                    31, 31, 31, 31, 31, 31, 31, 31, 31, 31, 31, 31, 31, 31, 31, 31,
                    31, 31, 31, 31, 31, 31, 31, 31, 31, 31, 31, 31, 31, 31, 31, 31,
                    31, 31, 31, 31, 31, 31, 31, 31, 31, 31, 31, 31, 31, 31, 31, 31,
                    31, 31, 31, 31, 31, 31, 31, 31, 31, 31, 31, 31, 31, 31, 31, 31,
                    31, 31, 31, 31, 31, 31, 31, 31, 31, 31, 31, 31, 31, 31, 31, 31,
                    31, 31, 31, 31, 31, 31, 31, 31, 31, 31, 31, 31, 31, 31, 31, 31,
                    0, 0, 0, 0, 0, 0, 0, 0, 0, 0, 0, 0, 0, 0, 0, 0,
                    0, 0, 0, 0, 0, 0, 0, 0, 0, 0, 0, 0, 0, 0, 0, 0,
                    0, 0, 0, 0, 0, 0, 0, 0, 0, 0, 0, 0, 0, 0, 0, 0,
                    0, 0, 0, 0, 0, 0, 0, 0, 0, 0, 0, 0, 0, 0, 0, 0],
                 "height":16,
                 "width":16,
                 "x":0,
                 "y":0
                }, 
                {
                 "data":[0, 0, 0, 0, 0, 0, 0, 0, 0, 0, 0, 0, 0, 0, 0, 0,
                    0, 0, 0, 0, 0, 0, 0, 0, 0, 0, 0, 0, 0, 0, 0, 0,
                    0, 0, 0, 0, 0, 0, 0, 0, 0, 0, 0, 0, 0, 0, 0, 0,
                    0, 0, 0, 0, 0, 0, 0, 0, 0, 0, 0, 0, 0, 0, 0, 0,
                    6, 6, 6, 6, 6, 6, 6, 6, 6, 6, 7, 0, 0, 0, 0, 0,
                    31, 31, 31, 31, 31, 31, 31, 31, 31, 31, 32, 0, 0, 0, 0, 0,
                    31, 31, 31, 31, 31, 31, 31, 31, 31, 31, 32, 0, 0, 0, 0, 0,
                    31, 31, 31, 31, 31, 31, 31, 31, 31, 31, 32, 0, 0, 0, 0, 0,
                    31, 31, 31, 31, 31, 31, 31, 31, 31, 31, 32, 0, 0, 0, 0, 0,
                    31, 31, 31, 31, 31, 31, 31, 31, 31, 31, 32, 0, 0, 0, 0, 0,
                    31, 31, 31, 31, 31, 31, 31, 31, 31, 31, 32, 0, 0, 0, 0, 0,
                    31, 31, 31, 31, 31, 31, 31, 31, 31, 31, 32, 0, 0, 0, 0, 0,
                    0, 0, 0, 0, 0, 0, 0, 0, 0, 0, 0, 0, 0, 0, 0, 0,
                    0, 0, 0, 0, 0, 0, 0, 0, 0, 0, 0, 0, 0, 0, 0, 0,
                    0, 0, 0, 0, 0, 0, 0, 0, 0, 0, 0, 0, 0, 0, 0, 0,
                    0, 0, 0, 0, 0, 0, 0, 0, 0, 0, 0, 0, 0, 0, 0, 0],
                 "height":16,
                 "width":16,
                 "x":16,
                 "y":0
                }],
         "height":16,
         "id":2,
         "name":"Floor",
         "opacity":1,
         "startx":-32,
         "starty":0,
         "type":"tilelayer",
         "visible":true,
         "width":64,
         "x":0,
         "y":0
        }, 
        {
         "chunks":[
                {
                 "data":[0, 0, 0, 0, 0, 0, 0, 0, 0, 0, 0, 0, 0, 0, 0, 0,
                    0, 0, 0, 0, 0, 0, 0, 0, 0, 0, 0, 0, 0, 0, 0, 0,
                    0, 0, 0, 0, 0, 0, 0, 0, 0, 0, 0, 0, 0, 0, 0, 0,
                    0, 0, 0, 0, 0, 0, 0, 0, 0, 0, 0, 0, 0, 0, 0, 0,
                    0, 0, 0, 0, 0, 0, 0, 0, 0, 0, 0, 0, 0, 0, 0, 0,
                    0, 0, 0, 0, 0, 0, 0, 0, 0, 0, 0, 308, 0, 0, 286, 0,
                    0, 0, 0, 0, 0, 0, 0, 0, 0, 0, 0, 0, 0, 0, 0, 0,
                    0, 0, 0, 0, 0, 0, 0, 0, 0, 0, 0, 0, 0, 285, 0, 286,
                    0, 0, 0, 0, 0, 0, 0, 0, 0, 0, 0, 0, 0, 0, 0, 0,
                    0, 0, 0, 0, 0, 0, 0, 0, 0, 0, 0, 0, 286, 0, 0, 0,
                    0, 0, 0, 0, 0, 0, 0, 0, 0, 0, 0, 84, 0, 0, 333, 0,
                    0, 0, 0, 0, 0, 0, 0, 0, 0, 0, 0, 84, 0, 0, 0, 0,
                    0, 0, 0, 0, 0, 0, 0, 0, 0, 0, 0, 0, 0, 0, 0, 0,
                    0, 0, 0, 0, 0, 0, 0, 0, 0, 0, 0, 0, 0, 0, 0, 0,
                    0, 0, 0, 0, 0, 0, 0, 0, 0, 0, 0, 0, 0, 0, 0, 0,
                    0, 0, 0, 0, 0, 0, 0, 0, 0, 0, 0, 0, 0, 0, 0, 0],
                 "height":16,
                 "width":16,
                 "x":-32,
                 "y":0
                }, 
                {
                 "data":[0, 0, 0, 0, 0, 0, 0, 0, 0, 0, 0, 0, 0, 0, 0, 0,
                    0, 0, 0, 0, 0, 0, 0, 0, 0, 0, 0, 0, 0, 0, 0, 0,
                    0, 0, 0, 0, 0, 0, 0, 0, 0, 0, 0, 0, 0, 0, 0, 0,
                    0, 0, 0, 0, 0, 0, 0, 0, 0, 0, 0, 0, 0, 0, 0, 0,
                    0, 0, 0, 0, 0, 0, 0, 0, 0, 0, 0, 0, 0, 0, 0, 0,
                    0, 0, 0, 0, 0, 0, 0, 0, 0, 0, 0, 0, 0, 0, 0, 0,
                    333, 0, 285, 0, 0, 0, 333, 0, 0, 0, 0, 0, 0, 0, 0, 286,
                    0, 0, 0, 0, 0, 0, 0, 309, 310, 0, 285, 286, 0, 0, 0, 0,
                    285, 333, 0, 0, 0, 0, 0, 334, 335, 0, 0, 0, 0, 0, 0, 0,
                    0, 286, 0, 0, 0, 0, 333, 0, 0, 0, 0, 0, 286, 0, 286, 286,
                    84, 0, 0, 0, 0, 0, 0, 0, 0, 0, 0, 0, 0, 0, 0, 0,
                    84, 0, 0, 285, 0, 0, 0, 0, 0, 285, 0, 0, 286, 0, 0, 0,
                    0, 0, 0, 0, 0, 0, 0, 0, 0, 0, 0, 0, 0, 0, 0, 0,
                    0, 0, 0, 0, 0, 0, 0, 0, 0, 0, 0, 0, 0, 0, 0, 0,
                    0, 0, 0, 0, 0, 0, 0, 0, 0, 0, 0, 0, 0, 0, 0, 0,
                    0, 0, 0, 0, 0, 0, 0, 0, 0, 0, 0, 0, 0, 0, 0, 0],
                 "height":16,
                 "width":16,
                 "x":-16,
                 "y":0
                }, 
                {
                 "data":[0, 0, 0, 0, 0, 0, 0, 0, 0, 0, 0, 0, 0, 0, 0, 0,
                    0, 0, 0, 0, 0, 0, 0, 0, 0, 0, 0, 0, 0, 0, 0, 0,
                    0, 0, 0, 0, 0, 0, 0, 0, 0, 0, 0, 0, 0, 0, 0, 0,
                    0, 0, 0, 0, 0, 0, 0, 0, 0, 0, 0, 0, 0, 0, 0, 0,
                    0, 0, 0, 0, 0, 0, 0, 0, 0, 0, 0, 0, 0, 0, 0, 0,
                    0, 0, 0, 0, 0, 0, 0, 0, 0, 0, 0, 0, 0, 285, 0, 0,
                    0, 0, 0, 0, 84, 285, 0, 0, 0, 0, 0, 0, 0, 0, 0, 0,
                    333, 0, 0, 0, 84, 0, 0, 0, 285, 0, 0, 285, 0, 0, 0, 286,
                    0, 0, 0, 286, 0, 286, 0, 0, 0, 0, 0, 0, 286, 0, 0, 0,
                    0, 0, 0, 0, 0, 0, 0, 0, 0, 0, 0, 0, 0, 0, 0, 0,
                    0, 0, 286, 0, 285, 0, 0, 0, 285, 0, 0, 0, 0, 0, 0, 0,
                    0, 0, 0, 0, 0, 0, 0, 0, 0, 0, 0, 333, 0, 285, 0, 0,
                    286, 0, 0, 0, 0, 0, 0, 0, 0, 0, 0, 0, 0, 0, 0, 0,
                    0, 0, 0, 0, 0, 0, 0, 0, 0, 0, 0, 0, 0, 0, 0, 0,
                    0, 0, 0, 0, 0, 0, 0, 0, 0, 0, 0, 0, 0, 0, 0, 0,
                    0, 0, 0, 0, 0, 0, 0, 0, 0, 0, 0, 0, 0, 0, 0, 0],
                 "height":16,
                 "width":16,
                 "x":0,
                 "y":0
                }, 
                {
                 "data":[0, 0, 0, 0, 0, 0, 0, 0, 0, 0, 0, 0, 0, 0, 0, 0,
                    0, 0, 0, 0, 0, 0, 0, 0, 0, 0, 0, 0, 0, 0, 0, 0,
                    0, 0, 0, 0, 0, 0, 0, 0, 0, 0, 0, 0, 0, 0, 0, 0,
                    0, 0, 0, 0, 0, 0, 0, 0, 0, 0, 0, 0, 0, 0, 0, 0,
                    0, 0, 0, 0, 0, 0, 0, 0, 0, 0, 0, 0, 0, 0, 0, 0,
                    0, 0, 0, 0, 286, 0, 0, 0, 0, 84, 0, 0, 0, 0, 0, 0,
                    0, 333, 0, 0, 0, 0, 0, 285, 0, 84, 0, 0, 0, 0, 0, 0,
                    0, 0, 286, 0, 0, 0, 0, 285, 0, 0, 0, 0, 0, 0, 0, 0,
                    0, 333, 0, 0, 0, 0, 0, 0, 0, 286, 0, 0, 0, 0, 0, 0,
                    0, 285, 0, 0, 0, 285, 0, 0, 0, 0, 0, 0, 0, 0, 0, 0,
                    0, 0, 0, 286, 84, 0, 333, 0, 258, 259, 0, 0, 0, 0, 0, 0,
                    0, 0, 0, 0, 84, 0, 285, 0, 283, 284, 0, 0, 0, 0, 0, 0,
                    0, 0, 0, 0, 0, 0, 0, 0, 0, 0, 0, 0, 0, 0, 0, 0,
                    0, 0, 0, 0, 0, 0, 0, 0, 0, 0, 0, 0, 0, 0, 0, 0,
                    0, 0, 0, 0, 0, 0, 0, 0, 0, 0, 0, 0, 0, 0, 0, 0,
                    0, 0, 0, 0, 0, 0, 0, 0, 0, 0, 0, 0, 0, 0, 0, 0],
                 "height":16,
                 "width":16,
                 "x":16,
                 "y":0
                }],
         "height":16,
         "id":3,
         "name":"Floor Details",
         "opacity":1,
         "startx":-32,
         "starty":0,
         "type":"tilelayer",
         "visible":true,
         "width":64,
         "x":0,
         "y":0
        }, 
        {
         "chunks":[
                {
                 "data":[0, 0, 0, 0, 0, 0, 0, 0, 0, 0, 0, 0, 0, 0, 0, 0,
                    0, 0, 0, 0, 0, 0, 0, 0, 0, 104, 1, 2, 2, 2, 2, 2,
                    0, 0, 0, 0, 0, 0, 0, 0, 0, 129, 26, 27, 27, 27, 27, 27,
                    0, 0, 0, 0, 0, 0, 0, 0, 0, 129, 51, 52, 52, 52, 52, 52,
                    0, 0, 0, 0, 0, 0, 0, 0, 0, 129, 0, 0, 0, 0, 0, 0,
                    0, 0, 0, 0, 0, 0, 0, 0, 0, 129, 0, 0, 0, 0, 0, 0,
                    0, 0, 0, 0, 0, 0, 0, 0, 0, 129, 0, 0, 0, 0, 0, 0,
                    0, 0, 0, 0, 0, 0, 0, 0, 0, 129, 0, 0, 0, 0, 0, 0,
                    0, 0, 0, 0, 0, 0, 0, 0, 0, 129, 0, 0, 0, 0, 0, 0,
                    0, 0, 0, 0, 0, 0, 0, 0, 0, 129, 0, 0, 0, 0, 0, 0,
                    0, 0, 0, 0, 0, 0, 0, 0, 0, 129, 0, 0, 0, 0, 0, 0,
                    0, 0, 0, 0, 0, 0, 0, 0, 0, 129, 0, 0, 0, 0, 0, 0,
                    0, 0, 0, 0, 0, 0, 0, 0, 0, 154, 77, 77, 77, 77, 77, 77,
                    0, 0, 0, 0, 0, 0, 0, 0, 0, 0, 0, 0, 0, 0, 0, 0,
                    0, 0, 0, 0, 0, 0, 0, 0, 0, 0, 0, 0, 0, 0, 0, 0,
                    0, 0, 0, 0, 0, 0, 0, 0, 0, 0, 0, 0, 0, 0, 0, 0],
                 "height":16,
                 "width":16,
                 "x":-32,
                 "y":0
                }, 
                {
                 "data":[0, 0, 0, 0, 0, 0, 0, 0, 0, 0, 0, 0, 0, 0, 0, 0,
                    2, 2, 2, 2, 2, 2, 2, 2, 2, 2, 2, 2, 3, 352, 1, 2,
                    27, 27, 27, 27, 27, 27, 27, 27, 27, 27, 27, 27, 28, 377, 26, 27,
                    52, 52, 52, 52, 52, 52, 52, 52, 52, 52, 52, 52, 53, 402, 51, 52,
                    0, 0, 0, 0, 0, 0, 0, 0, 0, 0, 0, 0, 0, 427, 0, 0,
                    0, 0, 0, 0, 0, 0, 0, 0, 0, 0, 0, 0, 0, 0, 0, 0,
                    0, 0, 0, 0, 0, 0, 0, 0, 0, 0, 0, 0, 0, 0, 0, 0,
                    0, 0, 0, 0, 0, 0, 0, 0, 0, 0, 0, 0, 0, 0, 0, 0,
                    0, 0, 0, 0, 0, 0, 0, 0, 0, 0, 0, 0, 0, 0, 0, 0,
                    0, 0, 0, 0, 0, 0, 0, 0, 0, 0, 0, 0, 0, 0, 0, 0,
                    0, 0, 0, 0, 0, 0, 0, 0, 0, 0, 0, 0, 0, 0, 0, 0,
                    0, 0, 0, 0, 0, 0, 0, 0, 0, 0, 0, 0, 0, 0, 0, 0,
                    77, 77, 77, 77, 77, 77, 77, 77, 77, 77, 77, 77, 77, 77, 77, 77,
                    0, 0, 0, 0, 0, 0, 0, 0, 0, 0, 0, 0, 0, 0, 0, 0,
                    0, 0, 0, 0, 0, 0, 0, 0, 0, 0, 0, 0, 0, 0, 0, 0,
                    0, 0, 0, 0, 0, 0, 0, 0, 0, 0, 0, 0, 0, 0, 0, 0],
                 "height":16,
                 "width":16,
                 "x":-16,
                 "y":0
                }, 
                {
                 "data":[0, 0, 0, 0, 0, 0, 0, 0, 0, 0, 0, 0, 0, 0, 0, 0,
                    2, 2, 2, 2, 2, 2, 3, 351, 1, 2, 2, 2, 2, 2, 2, 2,
                    27, 27, 27, 27, 27, 27, 28, 376, 26, 27, 27, 27, 27, 27, 27, 27,
                    52, 52, 452, 52, 52, 52, 53, 401, 51, 52, 52, 52, 52, 52, 52, 52,
                    0, 476, 477, 478, 0, 0, 0, 426, 0, 0, 0, 0, 0, 0, 0, 0,
                    0, 501, 502, 503, 0, 0, 0, 0, 0, 0, 0, 0, 0, 0, 0, 0,
                    0, 526, 527, 528, 0, 0, 0, 0, 0, 0, 0, 0, 0, 0, 0, 0,
                    0, 0, 0, 0, 0, 0, 0, 0, 0, 0, 0, 0, 0, 0, 0, 0,
                    0, 0, 0, 0, 0, 0, 0, 0, 0, 0, 0, 0, 0, 0, 0, 0,
                    0, 0, 0, 0, 0, 0, 0, 0, 0, 0, 0, 0, 0, 0, 0, 0,
                    0, 0, 0, 0, 0, 0, 0, 0, 0, 0, 0, 0, 0, 0, 0, 0,
                    0, 0, 0, 0, 0, 0, 0, 0, 0, 0, 0, 0, 0, 0, 0, 0,
                    77, 77, 77, 77, 77, 77, 77, 77, 77, 77, 77, 77, 77, 77, 77, 77,
                    0, 0, 0, 0, 0, 0, 0, 0, 0, 0, 0, 0, 0, 0, 0, 0,
                    0, 0, 0, 0, 0, 0, 0, 0, 0, 0, 0, 0, 0, 0, 0, 0,
                    0, 0, 0, 0, 0, 0, 0, 0, 0, 0, 0, 0, 0, 0, 0, 0],
                 "height":16,
                 "width":16,
                 "x":0,
                 "y":0
                }, 
                {
                 "data":[0, 0, 0, 0, 0, 0, 0, 0, 0, 0, 0, 0, 0, 0, 0, 0,
                    2, 2, 2, 2, 2, 2, 2, 2, 2, 2, 3, 105, 0, 0, 0, 0,
                    27, 27, 27, 27, 27, 27, 27, 27, 27, 27, 28, 130, 0, 0, 0, 0,
                    52, 52, 52, 52, 52, 52, 52, 52, 52, 52, 53, 130, 0, 0, 0, 0,
                    0, 0, 0, 0, 0, 0, 0, 0, 0, 0, 0, 130, 0, 0, 0, 0,
                    0, 0, 0, 0, 0, 0, 0, 0, 0, 0, 0, 130, 0, 0, 0, 0,
                    0, 0, 0, 0, 0, 0, 0, 0, 0, 0, 0, 130, 0, 0, 0, 0,
                    0, 0, 0, 0, 0, 0, 0, 0, 0, 0, 0, 130, 0, 0, 0, 0,
                    0, 0, 0, 0, 0, 0, 0, 0, 0, 0, 0, 130, 0, 0, 0, 0,
                    0, 0, 0, 0, 0, 0, 0, 0, 0, 0, 0, 130, 0, 0, 0, 0,
                    0, 0, 0, 0, 0, 0, 0, 0, 0, 0, 0, 130, 0, 0, 0, 0,
                    0, 0, 0, 0, 0, 0, 0, 0, 0, 0, 0, 130, 0, 0, 0, 0,
                    77, 77, 77, 77, 77, 77, 77, 77, 77, 77, 77, 155, 0, 0, 0, 0,
                    0, 0, 0, 0, 0, 0, 0, 0, 0, 0, 0, 0, 0, 0, 0, 0,
                    0, 0, 0, 0, 0, 0, 0, 0, 0, 0, 0, 0, 0, 0, 0, 0,
                    0, 0, 0, 0, 0, 0, 0, 0, 0, 0, 0, 0, 0, 0, 0, 0],
                 "height":16,
                 "width":16,
                 "x":16,
                 "y":0
                }],
         "height":32,
         "id":1,
         "name":"Walls",
         "opacity":1,
         "startx":-32,
         "starty":-16,
         "type":"tilelayer",
         "visible":true,
         "width":64,
         "x":0,
         "y":0
        }],
 "nextlayerid":4,
 "nextobjectid":1,
 "orientation":"orthogonal",
 "renderorder":"right-down",
 "tiledversion":"1.10.2",
 "tileheight":16,
 "tilesets":[
        {
         "firstgid":1,
         "source":"..\/dungeon_prison.json"
        }],
 "tilewidth":16,
 "type":"map",
 "version":"1.10",
 "width":30
}